encryptedcookie/__init__.py
encryptedcookie-1.1.dist-info/LICENSE
encryptedcookie-1.1.dist-info/METADATA
encryptedcookie-1.1.dist-info/WHEEL
encryptedcookie-1.1.dist-info/top_level.txt
encryptedcookie-1.1.dist-info/RECORD
